args/__init__.py
args/args.py
entrypoints/vg_tools.py
utils/__init__.py
utils/utils.py
vg_deployment/README.md
vg_deployment/__init__.py
vg_deployment/errors.sh
vg_deployment/site.yml
vg_deployment/group_vars/all
vg_deployment/python_ansible/__init__.py
vg_deployment/python_ansible/ansible.py
vg_deployment/roles/apache/handlers/main.yml
vg_deployment/roles/apache/tasks/main.yml
vg_deployment/roles/apache/templates/apache2-default.conf
vg_deployment/roles/apache/templates/apache2.conf
vg_deployment/roles/apache/templates/default_page.php
vg_deployment/roles/common/tasks/main.yml
vg_deployment/roles/firewall/handlers/main.yml
vg_deployment/roles/firewall/tasks/main.yml
vg_deployment/roles/firewall/templates/csf.conf
vg_deployment/roles/firewall/templates/csfpost.sh
vg_deployment/roles/initSwap/handlers/main.yml
vg_deployment/roles/initSwap/tasks/main.yml
vg_deployment/roles/letsencrypt/handlers/main.yml
vg_deployment/roles/letsencrypt/tasks/main.yml
vg_deployment/roles/logrotate/handlers/main.yml
vg_deployment/roles/logrotate/tasks/main.yml
vg_deployment/roles/logrotate/templates/reverse_proxy_rotate_log
vg_deployment/roles/mysql/handlers/main.yml
vg_deployment/roles/mysql/tasks/main.yml
vg_deployment/roles/mysql/templates/.my.cnf.j2
vg_deployment/roles/mysql/templates/RPM-GPG-KEY-mysql
vg_deployment/roles/mysql/templates/my.cnf.j2
vg_deployment/roles/mysql/templates/mysql-community.repo
vg_deployment/roles/php/handlers/main.yml
vg_deployment/roles/php/tasks/main.yml
vg_deployment/roles/php/templates/if.php
vg_deployment/roles/phpmyadmin/handlers/main.yml
vg_deployment/roles/phpmyadmin/tasks/main.yml
vg_deployment/roles/scripts/handlers/main.yml
vg_deployment/roles/scripts/tasks/main.yml
vg_deployment/roles/sftp/handlers/main.yml
vg_deployment/roles/sftp/tasks/main.yml
vg_deployment/roles/sftp/templates/sshd_config
vg_deployment/roles/vg_management/defaults/main.yml
vg_deployment/roles/vg_management/tasks/main.yml
vg_provisioning/README.md
vg_provisioning/__init__.py
vg_tools-0.1.0.post3.dist-info/licenses/LICENSE
vg_tools-0.1.0.post3.dist-info/METADATA
vg_tools-0.1.0.post3.dist-info/WHEEL
vg_tools-0.1.0.post3.dist-info/entry_points.txt
vg_tools-0.1.0.post3.dist-info/top_level.txt
vg_tools-0.1.0.post3.dist-info/RECORD
