Metadata-Version: 2.4
Name: vg_tools
Version: 0.1.0.post3
Summary: The Python script & library for managing web service stack
Author-email: swettoth0812 <tan@vnguru.com>
License-Expression: Apache-2.0
Requires-Python: >=3.10
License-File: LICENSE
Dynamic: license-file
